README.md
setup.cfg
setup.py
rekall/__init__.py
rekall/helpers.py
rekall/interval.py
rekall/interval_set.py
rekall/interval_set_mapping.py
rekall/predicates.py
rekall/runtime.py
rekall/bounds/__init__.py
rekall/bounds/abstract_bounds.py
rekall/bounds/bounds1D.py
rekall/bounds/bounds3D.py
rekall/bounds/utils.py
rekall/stdlib/__init__.py
rekall/stdlib/ingest.py
rekall/stdlib/merge_ops.py
rekall/stdlib/parsers.py
rekall/tuner/__init__.py
rekall/tuner/coordinate_descent.py
rekall/tuner/grid.py
rekall/tuner/hyperband.py
rekall/tuner/random.py
rekall/tuner/scipy_l_bfgs_b.py
rekall/tuner/scipy_nelder_mead.py
rekall/tuner/successive_halving.py
rekall/tuner/tuner.py
rekallpy.egg-info/PKG-INFO
rekallpy.egg-info/SOURCES.txt
rekallpy.egg-info/dependency_links.txt
rekallpy.egg-info/not-zip-safe
rekallpy.egg-info/requires.txt
rekallpy.egg-info/top_level.txt
test/test_interval_set.py
test/test_interval_set_mapping.py
test/test_list_predicates.py
test/test_logical_predicates.py
test/test_runtime.py
test/test_temporal_predicates.py