Metadata-Version: 1.0
Name: rekallpy
Version: 0.3.2
Summary: Compostional video event specification
Home-page: http://github.com/scanner-research/rekall
Author: Dan Fu
Author-email: danfu@cs.stanford.edu
License: Apache 2.0
Platform: UNKNOWN
